README.md
setup.py
pythonic_binance/__init__.py
pythonic_binance/client.py
pythonic_binance/exceptions.py
pythonic_binance/helpers.py
pythonic_binance.egg-info/PKG-INFO
pythonic_binance.egg-info/SOURCES.txt
pythonic_binance.egg-info/dependency_links.txt
pythonic_binance.egg-info/requires.txt
pythonic_binance.egg-info/top_level.txt