Metadata-Version: 1.1
Name: pythonic-binance
Version: 0.7.1
Summary: Binance REST API python implementation
Home-page: https://github.com/hANSIc99/pythonic-binance
Author: Sam McHardy
Author-email: UNKNOWN
License: MIT
Keywords: exchange rest api bitcoin ethereum btc eth neo
Platform: UNKNOWN
Classifier: Intended Audience :: Developers
Classifier: License :: OSI Approved :: MIT License
Classifier: Operating System :: OS Independent
Classifier: Programming Language :: Python :: 3
Classifier: Programming Language :: Python :: 3.4
Classifier: Programming Language :: Python :: 3.5
Classifier: Programming Language :: Python :: 3.6
Classifier: Programming Language :: Python :: 3.7
Classifier: Programming Language :: Python
Classifier: Topic :: Software Development :: Libraries :: Python Modules
